indent2dict/README.MD
indent2dict/__init__.py
indent2dict/requirements.txt
indent2dict/thirdparty.json
indent2dict-0.10.dist-info/LICENSE.rst
indent2dict-0.10.dist-info/METADATA
indent2dict-0.10.dist-info/WHEEL
indent2dict-0.10.dist-info/top_level.txt
indent2dict-0.10.dist-info/RECORD
