Metadata-Version: 2.1
Name: indent2dict
Version: 0.10
Summary: Converts an indented text or list of strings into a nested dictionary structure based on the indentation levels.
Home-page: https://github.com/hansalemaos/indent2dict
Author: Johannes Fischer
Author-email: aulasparticularesdealemaosp@gmail.com
License: MIT
Keywords: dict,string
Classifier: Development Status :: 4 - Beta
Classifier: Programming Language :: Python :: 3 :: Only
Classifier: Programming Language :: Python :: 3.10
Classifier: Topic :: Software Development :: Libraries :: Python Modules
Classifier: Topic :: Utilities
License-File: LICENSE.rst
Requires-Dist: flatten_any_dict_iterable_or_whatsoever
Requires-Dist: nested2nested
Requires-Dist: splitlistatindex
